pyspaceaware/.env.shared
pyspaceaware/Makefile
pyspaceaware/__init__.py
pyspaceaware/attitude.py
pyspaceaware/background.py
pyspaceaware/constants.py
pyspaceaware/constraints.py
pyspaceaware/coordinates.py
pyspaceaware/ctools/engine/BRDFRegistry.c
pyspaceaware/ctools/engine/LightCurveEngine.c
pyspaceaware/ctools/engine/Makefile
pyspaceaware/ctools/engine/engine_include/lightcurvelib.c
pyspaceaware/ctools/engine/engine_include/raylib.h
pyspaceaware/ctools/engine/engine_include/raymath.h
pyspaceaware/ctools/engine/engine_include/rcamera.h
pyspaceaware/ctools/engine/engine_include/rcore.c
pyspaceaware/ctools/engine/engine_include/rlgl.h
pyspaceaware/ctools/engine/engine_include/rlights.h
pyspaceaware/ctools/engine/engine_include/rmodels.c
pyspaceaware/ctools/engine/engine_include/rtextures.c
pyspaceaware/ctools/engine/engine_lib/libraylib.a
pyspaceaware/ctools/engine/engine_lib/libraylib_m1.a
pyspaceaware/ctools/engine/shaders/averaging.fs
pyspaceaware/ctools/engine/shaders/averaging.vs
pyspaceaware/ctools/engine/shaders/lighting.fs
pyspaceaware/ctools/engine/shaders/lighting.vs
pyspaceaware/ctools/engine/shaders/shadow_depth.fs
pyspaceaware/ctools/engine/shaders/shadow_depth.vs
pyspaceaware/ctools/synthetic/Makefile
pyspaceaware/ctools/synthetic/SyntheticRPO.c
pyspaceaware/ctools/synthetic/__init__.py
pyspaceaware/ctools/synthetic/setup.py
pyspaceaware/ctools/synthetic/shaders/base.vs
pyspaceaware/ctools/synthetic/shaders/blur.fs
pyspaceaware/ctools/synthetic/shaders/dof.fs
pyspaceaware/ctools/synthetic/shaders/lighting.fs
pyspaceaware/ctools/synthetic/shaders/lighting.vs
pyspaceaware/ctools/synthetic/shaders/shadow_depth.fs
pyspaceaware/ctools/synthetic/shaders/shadow_depth.vs
pyspaceaware/ctools/synthetic/synthetic_include/raylib.h
pyspaceaware/ctools/synthetic/synthetic_include/raymath.h
pyspaceaware/ctools/synthetic/synthetic_include/rcamera.h
pyspaceaware/ctools/synthetic/synthetic_include/rcore.c
pyspaceaware/ctools/synthetic/synthetic_include/rlgl.h
pyspaceaware-0.2.41.dist-info/LICENSE
pyspaceaware-0.2.41.dist-info/METADATA
pyspaceaware-0.2.41.dist-info/WHEEL
pyspaceaware-0.2.41.dist-info/RECORD
