Metadata-Version: 2.1
Name: pyspaceaware
Version: 0.2.41
Summary: A package for Space Domain Awareness simulation, including orbit and attitude propagation, catalog management, with a focus on generating light curves for human-made satellites and debris
Author: Liam Robinson
Author-email: robin502@purdue.edu
Requires-Python: >=3.8,<3.12
Classifier: License :: OSI Approved :: GNU General Public License v3 (GPLv3)
Classifier: Operating System :: MacOS
Classifier: Programming Language :: Python :: 3
Classifier: Programming Language :: Python :: 3.8
Classifier: Programming Language :: Python :: 3.9
Classifier: Programming Language :: Python :: 3.10
Classifier: Programming Language :: Python :: 3.11
Classifier: Programming Language :: Python :: 3
Requires-Dist: aiohttp (==3.8.4)
Requires-Dist: astropy (==5.2.2)
Requires-Dist: colorcet (==3.0.1)
Requires-Dist: numpy (==1.24.2)
Requires-Dist: pyembree (==0.1.12)
Requires-Dist: python-dotenv (==1.0.0)
Requires-Dist: pyvista (==0.38.5)
Requires-Dist: rtree (==1.0.1)
Requires-Dist: scipy (==1.10.1)
Requires-Dist: seaborn (>=0.12.2,<0.13.0)
Requires-Dist: sgp4 (==2.21)
Requires-Dist: spacetrack (==0.16.0)
Requires-Dist: terrainman (>=0.0.22,<0.0.23)
Requires-Dist: tqdm (==4.65.0)
Requires-Dist: trimesh (==3.21.5)
Project-URL: Documentation, https://liamrobinson1.github.io/pyspaceawaredocs/pyspaceaware.html
